andreadevEngine/__init__.py
andreadevEngine/andreadevEngine.py
andreadevEngine/Engine Default Assets/Button_defaultImage.png
andreadevEngine/Engine Default Assets/engine_fontManager.txt
andreadevEngine-1.0.0.dist-info/METADATA
andreadevEngine-1.0.0.dist-info/WHEEL
andreadevEngine-1.0.0.dist-info/top_level.txt
andreadevEngine-1.0.0.dist-info/RECORD
