Metadata-Version: 2.1
Name: andreadevEngine
Version: 1.0.0
Summary: Library to use on top of pygame. Uses GameObject and Component workflow
Home-page: https://github.com/AndreaMDev/AndreaDev-Phyton-Engine
Author: Andrea Manzone
Author-email: andmandev@gmail.com
License: UNKNOWN
Platform: UNKNOWN
Classifier: Programming Language :: Python
Classifier: Programming Language :: Python :: 3
Classifier: Programming Language :: Python :: 3.10
